Workbook

Sheet 持仓总表
A1: 序号 | B1: 股票名称 | C1: 成本价 | D1: 持仓股数 | E1: 现价 | F1: 盈亏比例 | G1: 持仓成本 | H1: 持仓市值 | I1: 盈亏额 | K1: 资金总额 | L1: 资金余额
A2: 1 | B2: 国光电气 | C2: 67.178465 | D2: 8300 | E2: 97.2 | F2: =I2/G2 | G2: =C2*D2 | H2: =E2*D2 | I2: =H2-C2*D2 | K2: 5000000 | L2: {=K2-SUMPRODUCT(C2:C201,D2:D201)} | M2: =IF(L2<=0,"余额不足","")
A3: 2 | B3: 宏微科技 | C3: 28.520842 | D3: 19240 | E3: 28.01 | F3: =I3/G3 | G3: =C3*D3 | H3: =E3*D3 | I3: =H3-C3*D3
A4: 3 | B4: 天岳先进 | C4: 71.27375 | D4: 4100 | E4: 85.75 | F4: =I4/G4 | G4: =C4*D4 | H4: =E4*D4 | I4: =H4-C4*D4 | K4: 股票名称 | L4: 求和项:持仓股数 | M4: 求和项:持仓市值
A5: 4 | B5: 联创光电 | C5: 58.95086 | D5: 6800 | E5: 58.57 | F5: =I5/G5 | G5: =C5*D5 | H5: =E5*D5 | I5: =H5-C5*D5 | K5: 概伦电子 | L5: 2500 | M5: 90250
A6: 5 | B6: 广立微 | C6: 77.65 | D6: 1300 | E6: 70.9 | F6: =I6/G6 | G6: =C6*D6 | H6: =E6*D6 | I6: =H6-C6*D6 | K6: 广立微 | L6: 1300 | M6: 91624
A7: 6 | B7: 华润微 | C7: 52.374113 | D7: 3948 | E7: 55.64 | F7: =I7/G7 | G7: =C7*D7 | H7: =E7*D7 | I7: =H7-C7*D7 | K7: 国光电气 | L7: 8300 | M7: 744676
A8: 7 | B8: 金宏气体 | C8: 20.453193 | D8: 9881 | E8: 19.85 | F8: =I8/G8 | G8: =C8*D8 | H8: =E8*D8 | I8: =H8-C8*D8 | K8: 国芯科技 | L8: 3400 | M8: 99858
A9: 8 | B9: 六九一二 | C9: 127.61 | D9: 1600 | E9: 116.5 | F9: =I9/G9 | G9: =C9*D9 | H9: =E9*D9 | I9: =H9-C9*D9 | K9: 合锻智能 | L9: 8800 | M9: 186120
A10: 9 | B10: 中国海防 | C10: 30.856284 | D10: 6400 | E10: 26.72 | F10: =I10/G10 | G10: =C10*D10 | H10: =E10*D10 | I10: =H10-C10*D10 | K10: 宏微科技 | L10: 19240 | M10: 444444
A11: 10 | B11: 梦洁股份 | C11: 4.42 | D11: 45400 | E11: 4.17 | F11: =I11/G11 | G11: =C11*D11 | H11: =E11*D11 | I11: =H11-C11*D11 | K11: 泓博医药 | L11: 5400 | M11: 176256
A12: 11 | B12: 山东黄金 | C12: 36.48578 | D12: 5500 | E12: 37.83 | F12: =I12/G12 | G12: =C12*D12 | H12: =E12*D12 | I12: =H12-C12*D12 | K12: 华润微 | L12: 3948 | M12: 191991.24
A13: 12 | B13: 斯达半导 | C13: 107.37041 | D13: 900 | E13: 95.13 | F13: =I13/G13 | G13: =C13*D13 | H13: =E13*D13 | I13: =H13-C13*D13 | K13: 金宏气体 | L13: 9881 | M13: 203746.22
A14: 13 | B14: 士兰微 | C14: 33.01 | D14: 3000 | E14: 28.14 | F14: =I14/G14 | G14: =C14*D14 | H14: =E14*D14 | I14: =H14-C14*D14 | K14: 联创光电 | L14: 6800 | M14: 402492
A15: 14 | B15: 泓博医药 | C15: 34.39 | D15: 5400 | E15: 30.65 | F15: =I15/G15 | G15: =C15*D15 | H15: =E15*D15 | I15: =H15-C15*D15 | K15: 联芸科技 | L15: 3600 | M15: 183924
A16: 15 | B16: 概伦电子 | C16: 40.436444 | D16: 2500 | E16: 35.23 | F16: =I16/G16 | G16: =C16*D16 | H16: =E16*D16 | I16: =H16-C16*D16 | K16: 六九一二 | L16: 1600 | M16: 196192
... A23: 22 | B23: 芯原股份 | C23: 155.4 | D23: 1400 | E23: 127.6 | F23: =I23/G23 | G23: =C23*D23 | H23: =E23*D23 | I23: =H23-C23*D23 | K23: 中国海防 | L23: 6400 | M23: 191232
A24: 23 | H24: =E24*D24 | I24: =H24-C24*D24 | K24: 中芯国际 | L24: 2400 | M24: 283632
A25: 24 | H25: =E25*D25 | I25: =H25-C25*D25 | K25: (空白) | M25: 0
A26: 25 | H26: =E26*D26 | I26: =H26-C26*D26 | K26: 梦洁股份 | L26: 45400 | M26: 196128
A27: 26 | H27: =E27*D27 | I27: =H27-C27*D27 | K27: 芯原股份 | L27: 1400 | M27: 213388
A28: 27 | H28: =E28*D28 | I28: =H28-C28*D28 | K28: 总计 | L28: 158269 | M28: 5266572.5
A29: 28 | H29: =E29*D29 | I29: =H29-C29*D29
A30: 29 | H30: =E30*D30 | I30: =H30-C30*D30
A31: 30 | H31: =E31*D31 | I31: =H31-C31*D31
A32: 31 | H32: =E32*D32 | I32: =H32-C32*D32
A33: 32 | H33: =E33*D33 | I33: =H33-C33*D33
A34: 33 | H34: =E34*D34 | I34: =H34-C34*D34
A35: 34 | H35: =E35*D35 | I35: =H35-C35*D35
A36: 35 | H36: =E36*D36 | I36: =H36-C36*D36
A37: 36 | H37: =E37*D37 | I37: =H37-C37*D37
A38: 37 | H38: =E38*D38 | I38: =H38-C38*D38
A39: 38 | H39: =E39*D39 | I39: =H39-C39*D39
A40: 39 | H40: =E40*D40 | I40: =H40-C40*D40
... A201: 200 | H201: =E201*D201 | I201: =H201-C201*D201
A202: 汇总 | D202: =SUM(D2:D201) | F202: =I202/G202 | G202: =SUM(G2:G201) | H202: =SUM(H2:H201) | I202: =SUM(I2:I201)

Sheet 当日交易记录
A1: 交易单号 | B1: 股票名称 | C1: 成交价格 | D1: 成交股数 | E1: 手续费 | F1: 交易收支 | G1: 当前持仓股数 | H1: 交易许可 | J1: 交易日期 | K1: =TODAY()
A2: 1 | B2: 中芯国际 | C2: 114.85 | D2: -800 | E2: =IF(B2="","",IF(D2<=0,-C2*D2*2.5/10000,C2*D2*12.5/10000)) | F2: =IF(B2="","",C2*D2-E2) | G2: =IF(B2="","",IF(COUNTIF(盘中持仓!B:B,B2),VLOOKUP(B2,盘中持仓!B:D,3,0),0)) | H2: =IF(B2="","",IF(G2<>0,IF(G2>0,"","交易超限"),"该股票未持仓，仅可买入")) | J2: 股票名称 | K2: 总卖出股数 | L2: 总盈亏
A3: 2 | E3: =IF(B3="","",IF(D3<=0,-C3*D3*2.5/10000,C3*D3*12.5/10000)) | F3: =IF(B3="","",C3*D3-E3) | G3: =IF(B3="","",IF(COUNTIF(盘中持仓!B:B,B3),VLOOKUP(B3,盘中持仓!B:D,3,0),0)) | H3: =IF(B3="","",IF(G3<>0,IF(G3>0,"","交易超限"),"该股票未持仓，仅可买入")) | J3: (空白) | L3: 0
A4: 3 | E4: =IF(B4="","",IF(D4<=0,-C4*D4*2.5/10000,C4*D4*12.5/10000)) | F4: =IF(B4="","",C4*D4-E4) | G4: =IF(B4="","",IF(COUNTIF(盘中持仓!B:B,B4),VLOOKUP(B4,盘中持仓!B:D,3,0),0)) | H4: =IF(B4="","",IF(G4<>0,IF(G4>0,"","交易超限"),"该股票未持仓，仅可买入")) | J4: 中芯国际 | K4: -800 | L4: -91902.97
A5: 4 | E5: =IF(B5="","",IF(D5<=0,-C5*D5*2.5/10000,C5*D5*12.5/10000)) | F5: =IF(B5="","",C5*D5-E5) | G5: =IF(B5="","",IF(COUNTIF(盘中持仓!B:B,B5),VLOOKUP(B5,盘中持仓!B:D,3,0),0)) | H5: =IF(B5="","",IF(G5<>0,IF(G5>0,"","交易超限"),"该股票未持仓，仅可买入")) | J5: 总计 | K5: -800 | L5: -91902.97
A6: 5 | E6: =IF(B6="","",IF(D6<=0,-C6*D6*2.5/10000,C6*D6*12.5/10000)) | F6: =IF(B6="","",C6*D6-E6) | G6: =IF(B6="","",IF(COUNTIF(盘中持仓!B:B,B6),VLOOKUP(B6,盘中持仓!B:D,3,0),0)) | H6: =IF(B6="","",IF(G6<>0,IF(G6>0,"","交易超限"),"该股票未持仓，仅可买入"))
A7: 6 | E7: =IF(B7="","",IF(D7<=0,-C7*D7*2.5/10000,C7*D7*12.5/10000)) | F7: =IF(B7="","",C7*D7-E7) | G7: =IF(B7="","",IF(COUNTIF(盘中持仓!B:B,B7),VLOOKUP(B7,盘中持仓!B:D,3,0),0)) | H7: =IF(B7="","",IF(G7<>0,IF(G7>0,"","交易超限"),"该股票未持仓，仅可买入"))
A8: 7 | E8: =IF(B8="","",IF(D8<=0,-C8*D8*2.5/10000,C8*D8*12.5/10000)) | F8: =IF(B8="","",C8*D8-E8) | G8: =IF(B8="","",IF(COUNTIF(盘中持仓!B:B,B8),VLOOKUP(B8,盘中持仓!B:D,3,0),0)) | H8: =IF(B8="","",IF(G8<>0,IF(G8>0,"","交易超限"),"该股票未持仓，仅可买入"))
A9: 8 | E9: =IF(B9="","",IF(D9<=0,-C9*D9*2.5/10000,C9*D9*12.5/10000)) | F9: =IF(B9="","",C9*D9-E9) | G9: =IF(B9="","",IF(COUNTIF(盘中持仓!B:B,B9),VLOOKUP(B9,盘中持仓!B:D,3,0),0)) | H9: =IF(B9="","",IF(G9<>0,IF(G9>0,"","交易超限"),"该股票未持仓，仅可买入"))
A10: 9 | E10: =IF(B10="","",IF(D10<=0,-C10*D10*2.5/10000,C10*D10*12.5/10000)) | F10: =IF(B10="","",C10*D10-E10) | G10: =IF(B10="","",IF(COUNTIF(盘中持仓!B:B,B10),VLOOKUP(B10,盘中持仓!B:D,3,0),0)) | H10: =IF(B10="","",IF(G10<>0,IF(G10>0,"","交易超限"),"该股票未持仓，仅可买入"))
A11: 10 | E11: =IF(B11="","",IF(D11<=0,-C11*D11*2.5/10000,C11*D11*12.5/10000)) | F11: =IF(B11="","",C11*D11-E11) | G11: =IF(B11="","",IF(COUNTIF(盘中持仓!B:B,B11),VLOOKUP(B11,盘中持仓!B:D,3,0),0)) | H11: =IF(B11="","",IF(G11<>0,IF(G11>0,"","交易超限"),"该股票未持仓，仅可买入"))
A12: 11 | E12: =IF(B12="","",IF(D12<=0,-C12*D12*2.5/10000,C12*D12*12.5/10000)) | F12: =IF(B12="","",C12*D12-E12) | G12: =IF(B12="","",IF(COUNTIF(盘中持仓!B:B,B12),VLOOKUP(B12,盘中持仓!B:D,3,0),0)) | H12: =IF(B12="","",IF(G12<>0,IF(G12>0,"","交易超限"),"该股票未持仓，仅可买入"))
A13: 12 | E13: =IF(B13="","",IF(D13<=0,-C13*D13*2.5/10000,C13*D13*12.5/10000)) | F13: =IF(B13="","",C13*D13-E13) | G13: =IF(B13="","",IF(COUNTIF(盘中持仓!B:B,B13),VLOOKUP(B13,盘中持仓!B:D,3,0),0)) | H13: =IF(B13="","",IF(G13<>0,IF(G13>0,"","交易超限"),"该股票未持仓，仅可买入"))
A14: 13 | E14: =IF(B14="","",IF(D14<=0,-C14*D14*2.5/10000,C14*D14*12.5/10000)) | F14: =IF(B14="","",C14*D14-E14) | G14: =IF(B14="","",IF(COUNTIF(盘中持仓!B:B,B14),VLOOKUP(B14,盘中持仓!B:D,3,0),0)) | H14: =IF(B14="","",IF(G14<>0,IF(G14>0,"","交易超限"),"该股票未持仓，仅可买入"))
A15: 14 | E15: =IF(B15="","",IF(D15<=0,-C15*D15*2.5/10000,C15*D15*12.5/10000)) | F15: =IF(B15="","",C15*D15-E15) | G15: =IF(B15="","",IF(COUNTIF(盘中持仓!B:B,B15),VLOOKUP(B15,盘中持仓!B:D,3,0),0)) | H15: =IF(B15="","",IF(G15<>0,IF(G15>0,"","交易超限"),"该股票未持仓，仅可买入"))
A16: 15 | E16: =IF(B16="","",IF(D16<=0,-C16*D16*2.5/10000,C16*D16*12.5/10000)) | F16: =IF(B16="","",C16*D16-E16) | G16: =IF(B16="","",IF(COUNTIF(盘中持仓!B:B,B16),VLOOKUP(B16,盘中持仓!B:D,3,0),0)) | H16: =IF(B16="","",IF(G16<>0,IF(G16>0,"","交易超限"),"该股票未持仓，仅可买入"))
A17: 16 | E17: =IF(B17="","",IF(D17<=0,-C17*D17*2.5/10000,C17*D17*12.5/10000)) | F17: =IF(B17="","",C17*D17-E17) | G17: =IF(B17="","",IF(COUNTIF(盘中持仓!B:B,B17),VLOOKUP(B17,盘中持仓!B:D,3,0),0)) | H17: =IF(B17="","",IF(G17<>0,IF(G17>0,"","交易超限"),"该股票未持仓，仅可买入"))
... A201: 200 | E201: =IF(B201="","",IF(D201<=0,-C201*D201*2.5/10000,C201*D201*12.5/10000)) | F201: =IF(B201="","",C201*D201-E201) | G201: =IF(B201="","",IF(COUNTIF(盘中持仓!B:B,B201),VLOOKUP(B201,盘中持仓!B:D,3,0),0)) | H201: =IF(B201="","",IF(G201<>0,IF(G201>0,"","交易超限"),"该股票未持仓，仅可买入"))

Sheet 盘中持仓
A1: 序号 | B1: 股票名称 | C1: 持仓成本 | D1: 持仓股数
A2: 1 | B2: =VLOOKUP(A2,持仓总表!A:B,2,0) | C2: =(持仓总表!C2*持仓总表!D2-SUMIF(当日交易记录!B:B,B2,当日交易记录!F:F))/D2 | D2: =持仓总表!D2-SUMIF(当日交易记录!B:B,B2,当日交易记录!D:D)
A3: 2 | B3: =VLOOKUP(A3,持仓总表!A:B,2,0) | C3: =(持仓总表!C3*持仓总表!D3-SUMIF(当日交易记录!B:B,B3,当日交易记录!F:F))/D3 | D3: =持仓总表!D3-SUMIF(当日交易记录!B:B,B3,当日交易记录!D:D)
A4: 3 | B4: =VLOOKUP(A4,持仓总表!A:B,2,0) | C4: =(持仓总表!C4*持仓总表!D4-SUMIF(当日交易记录!B:B,B4,当日交易记录!F:F))/D4 | D4: =持仓总表!D4-SUMIF(当日交易记录!B:B,B4,当日交易记录!D:D)
A5: 4 | B5: =VLOOKUP(A5,持仓总表!A:B,2,0) | C5: =(持仓总表!C5*持仓总表!D5-SUMIF(当日交易记录!B:B,B5,当日交易记录!F:F))/D5 | D5: =持仓总表!D5-SUMIF(当日交易记录!B:B,B5,当日交易记录!D:D)
A6: 5 | B6: =VLOOKUP(A6,持仓总表!A:B,2,0) | C6: =(持仓总表!C6*持仓总表!D6-SUMIF(当日交易记录!B:B,B6,当日交易记录!F:F))/D6 | D6: =持仓总表!D6-SUMIF(当日交易记录!B:B,B6,当日交易记录!D:D)
A7: 6 | B7: =VLOOKUP(A7,持仓总表!A:B,2,0) | C7: =(持仓总表!C7*持仓总表!D7-SUMIF(当日交易记录!B:B,B7,当日交易记录!F:F))/D7 | D7: =持仓总表!D7-SUMIF(当日交易记录!B:B,B7,当日交易记录!D:D)
A8: 7 | B8: =VLOOKUP(A8,持仓总表!A:B,2,0) | C8: =(持仓总表!C8*持仓总表!D8-SUMIF(当日交易记录!B:B,B8,当日交易记录!F:F))/D8 | D8: =持仓总表!D8-SUMIF(当日交易记录!B:B,B8,当日交易记录!D:D)
A9: 8 | B9: =VLOOKUP(A9,持仓总表!A:B,2,0) | C9: =(持仓总表!C9*持仓总表!D9-SUMIF(当日交易记录!B:B,B9,当日交易记录!F:F))/D9 | D9: =持仓总表!D9-SUMIF(当日交易记录!B:B,B9,当日交易记录!D:D)
A10: 9 | B10: =VLOOKUP(A10,持仓总表!A:B,2,0) | C10: =(持仓总表!C10*持仓总表!D10-SUMIF(当日交易记录!B:B,B10,当日交易记录!F:F))/D10 | D10: =持仓总表!D10-SUMIF(当日交易记录!B:B,B10,当日交易记录!D:D)
A11: 10 | B11: =VLOOKUP(A11,持仓总表!A:B,2,0) | C11: =(持仓总表!C11*持仓总表!D11-SUMIF(当日交易记录!B:B,B11,当日交易记录!F:F))/D11 | D11: =持仓总表!D11-SUMIF(当日交易记录!B:B,B11,当日交易记录!D:D)
A12: 11 | B12: =VLOOKUP(A12,持仓总表!A:B,2,0) | C12: =(持仓总表!C12*持仓总表!D12-SUMIF(当日交易记录!B:B,B12,当日交易记录!F:F))/D12 | D12: =持仓总表!D12-SUMIF(当日交易记录!B:B,B12,当日交易记录!D:D)
A13: 12 | B13: =VLOOKUP(A13,持仓总表!A:B,2,0) | C13: =(持仓总表!C13*持仓总表!D13-SUMIF(当日交易记录!B:B,B13,当日交易记录!F:F))/D13 | D13: =持仓总表!D13-SUMIF(当日交易记录!B:B,B13,当日交易记录!D:D)
... A201: 200 | B201: =VLOOKUP(A201,持仓总表!A:B,2,0) | C201: =(持仓总表!C201*持仓总表!D201-SUMIF(当日交易记录!B:B,B201,当日交易记录!F:F))/D201 | D201: =持仓总表!D201-SUMIF(当日交易记录!B:B,B201,当日交易记录!D:D)
